forge/__init__.py
forge/cli.py
forge/agent/__init__.py
forge/agent/prompt.py
forge/agent/test_workflow.py
forge/agent/workflow.py
forge/config/__init__.py
forge/config/config.py
forge/config/constants.py
forge/tools/__init__.py
forge/tools/tool_utils.py
forge/tools/tools.py
forge/utils/__init__.py
forge/utils/utils.py
forge_ai-1.1.0.dist-info/licenses/LICENSE
forge_ai-1.1.0.dist-info/METADATA
forge_ai-1.1.0.dist-info/WHEEL
forge_ai-1.1.0.dist-info/entry_points.txt
forge_ai-1.1.0.dist-info/top_level.txt
forge_ai-1.1.0.dist-info/RECORD
