Metadata-Version: 2.4
Name: forge-ai
Version: 1.1.0
Summary: An AI coding agent that can inspect, reason about, and modify your codebase.
Author: Shiwang Upadhyay
Author-email: shiwangupadhyay8@gmail.com
Project-URL: Homepage, https://github.com/shiwangupadhyay/forge_ai
Project-URL: Repository, https://github.com/shiwangupadhyay/forge_ai
Project-URL: Issues, https://github.com/shiwangupadhyay/forge_ai/issues
Keywords: forge,forge-ai,ai,openai,gemini,automation,developer-tools,cli,agent,cli-agent,coding-agent
Classifier: Programming Language :: Python :: 3
Classifier: Operating System :: OS Independent
Requires-Python: >=3.8
License-File: LICENSE
Requires-Dist: langchain-core
Requires-Dist: langgraph
Requires-Dist: langchain-google-genai
Requires-Dist: langchain-openai
Requires-Dist: langchain-anthropic
Requires-Dist: typer[all]
Requires-Dist: rich
Requires-Dist: langgraph-checkpoint-sqlite
Provides-Extra: docify-ai
Requires-Dist: docify-ai; extra == "docify-ai"
Provides-Extra: all
Requires-Dist: docify-ai; extra == "all"
Dynamic: license-file
